{
    "260698308595726336": {
        "733551377611096195": {
            "wins": "0",
            "kills": "0",
            "deaths": "0",
            "totalExp": "0"
        },
        "299742581972271104": {
            "wins": "0",
            "kills": "0",
            "deaths": "0",
            "totalExp": "0"
        }
    },
    "260698008595726336": {
        "299742581972271104": {
            "wins": "0",
            "kills": "0",
            "deaths": "0",
            "totalExp": "0"
        }
    }
}